fastapi_bunny/__init__.py
fastapi_bunny/generate.py
fastapi_bunny-0.1.4.dist-info/METADATA
fastapi_bunny-0.1.4.dist-info/WHEEL
fastapi_bunny-0.1.4.dist-info/entry_points.txt
fastapi_bunny-0.1.4.dist-info/top_level.txt
fastapi_bunny-0.1.4.dist-info/RECORD
