Metadata-Version: 2.2
Name: fastapi_bunny
Version: 0.1.4
Summary: A package to generate FastAPI boilerplate based on user input
Home-page: https://github.com/pranayvartak/fastapi_bunny
Author: Pranay Vartak
Author-email: iamvartak@gmail.com
Classifier: Programming Language :: Python :: 3
Classifier: License :: OSI Approved :: MIT License
Classifier: Operating System :: OS Independent
Requires-Python: >=3.7
Requires-Dist: fastapi
Requires-Dist: pymongo
Requires-Dist: pydantic
Requires-Dist: uvicorn[standard]
Dynamic: author
Dynamic: author-email
Dynamic: classifier
Dynamic: description
Dynamic: description-content-type
Dynamic: home-page
Dynamic: requires-dist
Dynamic: requires-python
Dynamic: summary
